ml_exp_comparator/__init__.py
ml_exp_comparator/expertiments_runner.py
ml_exp_comparator/dataset_stores/__init__.py
ml_exp_comparator/dataset_stores/dataset_store.py
ml_exp_comparator/dataset_stores/mnist_dataset_store.py
ml_exp_comparator/metrics_runners/__init__.py
ml_exp_comparator/metrics_runners/accuracy_metric_runner.py
ml_exp_comparator/metrics_runners/bin_accuracy_metric_runner.py
ml_exp_comparator/metrics_runners/metric_runner.py
ml_exp_comparator/metrics_runners/mnist_accuracy_metric_runner.py
ml_exp_comparator/models_runners/__init__.py
ml_exp_comparator/models_runners/model_runner.py
ml_exp_comparator/models_runners/simple_model_runner.py
ml_exp_comparator/results_aggregators/__init__.py
ml_exp_comparator/results_aggregators/results_aggregator.py
ml_exp_comparator/results_aggregators/table_results_aggregator.py
ml_exp_comparator-1.0.1.dist-info/LICENSE
ml_exp_comparator-1.0.1.dist-info/METADATA
ml_exp_comparator-1.0.1.dist-info/WHEEL
ml_exp_comparator-1.0.1.dist-info/top_level.txt
ml_exp_comparator-1.0.1.dist-info/RECORD
