Metadata-Version: 2.1
Name: ml_exp_comparator
Version: 1.0.1
Summary: Compare ML experiments
Author-email: Max Kalganov <maksim.kalganov@gmail.com>
License: The MIT License (MIT)
Project-URL: repository, https://github.com/max-kalganov/ml_exp_comparator
Keywords: ML,DS,Machine Learning,Data Science,Experiments,Compare
Classifier: License :: OSI Approved :: MIT License
Classifier: Programming Language :: Python
Classifier: Programming Language :: Python :: 3
Requires-Python: >=3.7
License-File: LICENSE
Requires-Dist: pandas
Requires-Dist: numpy
Provides-Extra: mnist
Requires-Dist: tensorflow >=2.14 ; extra == 'mnist'
